LICENSE
LICENSE.unidic
README.md
setup.py
unidic_lite/__init__.py
unidic_lite/unidic.py
unidic_lite.egg-info/PKG-INFO
unidic_lite.egg-info/SOURCES.txt
unidic_lite.egg-info/dependency_links.txt
unidic_lite.egg-info/top_level.txt
unidic_lite/dicdir/AUTHORS
unidic_lite/dicdir/BSD
unidic_lite/dicdir/COPYING
unidic_lite/dicdir/ChangeLog
unidic_lite/dicdir/GPL
unidic_lite/dicdir/INSTALL
unidic_lite/dicdir/LGPL
unidic_lite/dicdir/README.md
unidic_lite/dicdir/char.bin
unidic_lite/dicdir/dicrc
unidic_lite/dicdir/matrix.bin
unidic_lite/dicdir/mecabrc
unidic_lite/dicdir/sys.dic
unidic_lite/dicdir/unidic-mecab.pdf
unidic_lite/dicdir/unk.dic
unidic_lite/dicdir/version