Metadata-Version: 2.1
Name: unidic-lite
Version: 1.0.7
Summary: A small version of UniDic packaged for Python
Home-page: https://github.com/polm/unidic-lite
Author: Paul O'Leary McCann
Author-email: polm@dampfkraft.com
License: UNKNOWN
Platform: UNKNOWN
Classifier: Programming Language :: Python :: 3
Classifier: License :: OSI Approved :: MIT License
Classifier: Operating System :: OS Independent
Classifier: Natural Language :: Japanese
